Metadata-Version: 1.1
Name: CheckRequest
Version: 0.0.1
Summary: A connection checker
Home-page: UNKNOWN
Author: Algrow
Author-email: nobody@needsit.com
License: MIT
Keywords: connection
Platform: UNKNOWN
Classifier: Development Status :: 5 - Production/Stable
Classifier: Intended Audience :: Education
Classifier: License :: OSI Approved :: MIT License
Classifier: Programming Language :: Python :: 3
